GpsAndMap/GpsModule.py
GpsAndMap/MapModule.py
GpsAndMap/__init__.py
gpsandmap-4.0.0.dist-info/licenses/LICENSE
gpsandmap-4.0.0.dist-info/METADATA
gpsandmap-4.0.0.dist-info/WHEEL
gpsandmap-4.0.0.dist-info/top_level.txt
gpsandmap-4.0.0.dist-info/RECORD
