Metadata-Version: 2.4
Name: GpsAndMap
Version: 4.0.0
Summary: 提供了一个封装了GPS坐标值与坐标系数据的GSP类，提供了一个基于 folium 二次封装的地图类
Author-email: douyaoyuan <douyaoyuan@126.com>
License-Expression: MIT
Project-URL: Homepage, https://gitee.com/DyyYq/GpsAndMap
Project-URL: Bug Tracker, https://gitee.com/DyyYq/GpsAndMap/issues
Classifier: Programming Language :: Python :: 3
Classifier: Operating System :: OS Independent
Requires-Python: >=3.8
License-File: LICENSE
Requires-Dist: debugInfo
Requires-Dist: folium
Dynamic: license-file
